{"dimensions":[4],"layers":[{"type":"logistic","size":20,"weights":{"W":[[null,null,null,null],[null,null,null,null],[null,null,null,null],[null,null,null,null],[0,0,0,0],[0,0,0,0],[0,0,0,0],[0,0,0,0],[0,0,0,0],[0,0,0,0],[0,0,0,0],[0,0,0,0],[0,0,0,0],[0,0,0,0],[0,0,0,0],[0,0,0,0],[0,0,0,0],[0,0,0,0],[0,0,0,0],[0,0,0,0]],"b":[[null],[0],[0],[0],[0],[0],[0],[0],[0],[0],[0],[0],[0],[0],[0],[0],[0],[0],[0],[0]]}},{"type":"logistic","size":15,"weights":{"W":[[null,null,null,null,null,null,null,null,null,null,null,null,null,null,null,0,0,0,0,0],[null,null,null,null,null,null,null,null,null,null,null,null,null,null,null,0,0,0,0,0],[null,null,null,null,null,null,null,null,null,null,null,null,null,null,null,0,0,0,0,0],[null,null,null,null,null,null,null,null,null,null,null,null,null,null,null,0,0,0,0,0],[null,null,null,null,null,null,null,null,null,null,null,null,null,null,null,0,0,0,0,0],[null,null,null,null,null,null,null,null,null,null,null,null,null,null,null,0,0,0,0,0],[null,null,null,null,null,null,null,null,null,null,null,null,null,null,null,0,0,0,0,0],[null,null,null,null,null,null,null,null,null,null,null,null,null,null,null,0,0,0,0,0],[null,null,null,null,null,null,null,null,null,null,null,null,null,null,null,0,0,0,0,0],[null,null,null,null,null,null,null,null,null,null,null,null,null,null,null,0,0,0,0,0],[null,null,null,null,null,null,null,null,null,null,0.032195123487707235,0.019265662669876372,-0.04050358166122958,-0.019020788765670083,0.04273707916231211,0,0,0,0,0],[null,null,null,null,null,null,null,null,null,null,0.003999089211054363,0.014275266507147123,-0.006291466630500931,0.01982563273722389,0.015124925799361711,0,0,0,0,0],[null,null,null,null,null,null,null,null,null,null,-0.03290647922149908,0.02052353179620219,-0.030450746154981223,-0.049716377387854754,0.021528494209023075,0,0,0,0,0],[null,null,null,null,null,null,null,null,null,null,-0.012001112069972742,0.035036465976789576,-0.022950183189744223,0.04301349354868283,0.009050363607749601,0,0,0,0,0],[null,null,null,null,null,null,null,null,null,null,0.04241679488095218,0.022719917775746848,0.049627060082137665,0.010668414361746238,0.04509075672129612,0,0,0,0,0]],"b":[[null],[0],[0],[0],[0],[0],[0],[0],[0],[0],[0],[0],[0],[0],[0]]}},{"type":"logistic","size":10,"weights":{"W":[[null,null,null,null,null,null,null,null,null,null,0,0,0,0,0],[null,null,null,null,null,null,null,null,null,null,0,0,0,0,0],[null,null,null,null,null,null,null,null,null,null,0,0,0,0,0],[null,null,null,null,null,null,null,null,null,null,0,0,0,0,0],[null,null,null,null,null,null,null,null,null,null,0,0,0,0,0],[null,null,null,null,null,null,null,null,null,null,0,0,0,0,0],[null,null,null,null,null,null,null,null,null,null,0,0,0,0,0],[null,null,null,null,null,null,null,null,null,null,0,0,0,0,0],[null,null,null,null,null,null,null,null,null,null,0,0,0,0,0],[null,null,null,null,null,null,null,null,null,null,0,0,0,0,0]],"b":[[null],[0],[0],[0],[0],[0],[0],[0],[0],[0]]}},{"type":"logistic","size":3,"weights":{"W":[[null,null,null,0,0,0,0,0,0,0],[null,null,null,0,0,0,0,0,0,0],[null,null,null,0,0,0,0,0,0,0]],"b":[[null],[0],[0]]}}]}